captcha_bypass/__init__.py
captcha_bypass/__main__.py
captcha_bypass/cli.py
captcha_bypass/server.py
captcha_bypass/solver.py
captcha_bypass/storage.py
captcha_bypass/client/__init__.py
captcha_bypass/client/async_client.py
captcha_bypass/client/exceptions.py
captcha_bypass/client/response.py
captcha_bypass/client/sync_client.py
captcha_bypass-0.2.0.dist-info/METADATA
captcha_bypass-0.2.0.dist-info/WHEEL
captcha_bypass-0.2.0.dist-info/entry_points.txt
captcha_bypass-0.2.0.dist-info/licenses/LICENSE
captcha_bypass-0.2.0.dist-info/RECORD
