Metadata-Version: 2.4
Name: captcha-bypass
Version: 0.2.0
Summary: Self-hosted async captcha bypass service with HTTP API
Project-URL: Homepage, https://github.com/mspanchenko/captcha-bypass
Project-URL: Repository, https://github.com/mspanchenko/captcha-bypass
Author-email: mspanchenko <maxpanchnko@gmail.com>
License: Captcha-Bypass License v1.0
License-File: LICENSE
Keywords: anti-bot,bypass,camoufox,captcha,cloudflare
Classifier: Development Status :: 3 - Alpha
Classifier: Environment :: Console
Classifier: Framework :: aiohttp
Classifier: Intended Audience :: Developers
Classifier: License :: Other/Proprietary License
Classifier: Operating System :: OS Independent
Classifier: Programming Language :: Python :: 3
Classifier: Programming Language :: Python :: 3.12
Classifier: Programming Language :: Python :: 3.13
Classifier: Programming Language :: Python :: 3.14
Classifier: Topic :: Internet :: WWW/HTTP
Requires-Python: >=3.12
Requires-Dist: aiohttp>=3.9.0
Requires-Dist: camoufox[geoip]>=0.4.0
Requires-Dist: psutil>=5.9.0
Requires-Dist: requests>=2.28.0
